kundoluk_api/exceptions.py
kundoluk_api/kundoluk_warnings.py
kundoluk_api/test2.py
kundoluk_api/api/__init__.py
kundoluk_api/api/clients.py
kundoluk_api/api/student/async_student_client.py
kundoluk_api/api/student/base_student.py
kundoluk_api/api/student/student_client.py
kundoluk_api/enums/__init__.py
kundoluk_api/enums/absent_type.py
kundoluk_api/enums/mark_type.py
kundoluk_api/models/__init__.py
kundoluk_api/models/daily_schedule.py
kundoluk_api/models/daily_schedules.py
kundoluk_api/models/kundoluk_account.py
kundoluk_api/models/kundoluk_response.py
kundoluk_api/models/lesson.py
kundoluk_api/models/lesson_teacher.py
kundoluk_api/models/mark.py
kundoluk_api/models/marks.py
kundoluk_api/models/quarter_mark.py
kundoluk_api/models/quarter_marks.py
kundoluk_api/models/quarter_marks_result.py
kundoluk_api/models/quarter_marks_results.py
kundoluk_api/models/room.py
kundoluk_api/models/school.py
kundoluk_api/models/student.py
kundoluk_api/models/subject.py
kundoluk_api/models/task.py
kundoluk_api/models/teacher.py
kundoluk_api/models/topic.py
kundoluk_api/utils/parsers.py
kundoluk_api/utils/school_year.py
kundoluk_api-0.1.3.dist-info/METADATA
kundoluk_api-0.1.3.dist-info/WHEEL
kundoluk_api-0.1.3.dist-info/top_level.txt
kundoluk_api-0.1.3.dist-info/RECORD
