Metadata-Version: 2.4
Name: kundoluk_api
Version: 0.1.3
Summary: Библиотека для работы с API электронного журнала Кундолук (Кыргызстан), предоставляющая Python-интерфейс для получения расписания, оценок и учебной информации студентами.
Author: Umar
License: Proprietary
Project-URL: Homepage, https://github.com/Umar151515/kundoluk_api
Project-URL: Repository, https://github.com/Umar151515/kundoluk_api
Platform: any
Requires-Python: >=3.8
Requires-Dist: httpx<1.0.0
